powerplantsim/__init__.py
powerplantsim/datatypes/__init__.py
powerplantsim/datatypes/datatype.py
powerplantsim/datatypes/edge.py
powerplantsim/datatypes/extremity.py
powerplantsim/datatypes/machine.py
powerplantsim/datatypes/node.py
powerplantsim/datatypes/storage.py
powerplantsim/plant/__init__.py
powerplantsim/plant/action.py
powerplantsim/plant/callback.py
powerplantsim/plant/drawing.py
powerplantsim/plant/execution.py
powerplantsim/plant/plant.py
powerplantsim/utils/__init__.py
powerplantsim/utils/matching.py
powerplantsim/utils/strings.py
powerplantsim/utils/typing.py
powerplantsim-0.1.2.dist-info/METADATA
powerplantsim-0.1.2.dist-info/WHEEL
powerplantsim-0.1.2.dist-info/licenses/LICENSE
powerplantsim-0.1.2.dist-info/RECORD
