Metadata-Version: 2.1
Name: powerplantsim
Version: 0.1.2
Summary: PowerPlantSim: a power plant simulator
Project-URL: Repository, https://github.com/giuluck/powerplantsim/
Author: University of Bologna - DISI
Author-email: Luca Giuliani <luca.giuliani13@unibo.it>
Maintainer-email: Luca Giuliani <luca.giuliani13@unibo.it>
License: MIT License
License-File: LICENSE
Requires-Python: >=3.10
Requires-Dist: dickens>=2.0
Requires-Dist: matplotlib>=3.7
Requires-Dist: networkx>=2.7
Requires-Dist: numpy>=1.22
Requires-Dist: pandas>=1.4
Requires-Dist: pyomo>=6.6
Requires-Dist: scikit-learn>=1.1
Requires-Dist: tqdm>=4.7
